tfutility/__init__.py
tfutility/main.py
tfutility/contrib/deprecation.py
tfutility/controllers/__init__.py
tfutility/controllers/blockdate.py
tfutility/controllers/forcedremotesource.py
tfutility/controllers/sourceswap.py
tfutility/core/abstract.py
tfutility/core/base.py
tfutility/core/exp.py
tfutility/core/tffile.py
tfutility/core/tfpaths.py
tfutility-1.2.1.dist-info/LICENSE
tfutility-1.2.1.dist-info/METADATA
tfutility-1.2.1.dist-info/WHEEL
tfutility-1.2.1.dist-info/entry_points.txt
tfutility-1.2.1.dist-info/top_level.txt
tfutility-1.2.1.dist-info/RECORD
