Metadata-Version: 2.1
Name: tfutility
Version: 1.2.1
Summary: TfUtility provides different tools for Terraform Developers
Author-email: Stefan Eiermann <stefan.eiermann@eneka.de>
License:                     GNU AFFERO GENERAL PUBLIC LICENSE
Project-URL: Homepage, https://github.com/eieste/tfutility/
Project-URL: Documentation, https://eieste.github.io/tfutility/
Project-URL: Repo, https://github.com/eieste/tfutility
Project-URL: Issues, https://github.com/eieste/tfutility/issues
Classifier: Development Status :: 4 - Beta
Classifier: Intended Audience :: Developers
Classifier: Intended Audience :: System Administrators
Classifier: Topic :: Software Development :: Build Tools
Classifier: License :: OSI Approved :: GNU Affero General Public License v3 or later (AGPLv3+)
Classifier: Programming Language :: Python :: 3.10
Classifier: Programming Language :: Python :: 3.11
Classifier: Programming Language :: Python :: 3.12
Classifier: Programming Language :: Python :: 3.13
License-File: LICENSE
Requires-Dist: python-hcl2==4.3.5
Requires-Dist: argcomplete==3.5.1
Provides-Extra: dev
Requires-Dist: pytest==8.3.3; extra == "dev"
Requires-Dist: pytest-mock==3.14.0; extra == "dev"
Requires-Dist: pytest-cov==6.0.0; extra == "dev"
Requires-Dist: coverage==7.6.6; extra == "dev"
Requires-Dist: pre_commit==4.0.1; extra == "dev"
Requires-Dist: sphinx==8.1.3; extra == "dev"
Requires-Dist: sphinx-argparse==0.5.2; extra == "dev"
Requires-Dist: sphinx-autobuild==2024.10.3; extra == "dev"
Requires-Dist: sphinx-toolbox==3.8.1; extra == "dev"
Requires-Dist: sphinx-rtd-theme==3.0.2; extra == "dev"
Requires-Dist: setuptools>=70.0.0; extra == "dev"
